nixpkgs_pytools/__init__.py
nixpkgs_pytools/dependency.py
nixpkgs_pytools/download.py
nixpkgs_pytools/format.py
nixpkgs_pytools/import_rewrite.py
nixpkgs_pytools/output.py
nixpkgs_pytools/python_package_init.py
nixpkgs_pytools/utils.py
nixpkgs_pytools-1.3.0.dist-info/LICENSE
nixpkgs_pytools-1.3.0.dist-info/METADATA
nixpkgs_pytools-1.3.0.dist-info/WHEEL
nixpkgs_pytools-1.3.0.dist-info/entry_points.txt
nixpkgs_pytools-1.3.0.dist-info/top_level.txt
nixpkgs_pytools-1.3.0.dist-info/RECORD
