Metadata-Version: 2.1
Name: nixpkgs-pytools
Version: 1.3.0
Summary: Tools for removing the tedious nature of creating nixpkgs derivations
Home-page: https://github.com/nix-community/nixpkgs-pytools/
Author: Christopher Ostrouchov
Author-email: chris.ostrouchov@gmail.com
License: MIT
Platform: UNKNOWN
Classifier: Natural Language :: English
Classifier: Intended Audience :: Developers
Classifier: Operating System :: POSIX :: Linux
Classifier: Development Status :: 3 - Alpha
Classifier: License :: OSI Approved :: MIT License
Classifier: Programming Language :: Python
Classifier: Programming Language :: Python :: 2.7
Classifier: Programming Language :: Python :: 3.5
Classifier: Programming Language :: Python :: 3.6
Classifier: Programming Language :: Python :: 3.7
Classifier: Programming Language :: Python :: Implementation :: CPython
Classifier: Topic :: Software Development :: Code Generators
Classifier: Topic :: System :: Software Distribution
Requires-Dist: jinja2
Requires-Dist: setuptools
Requires-Dist: rope
